Toolbox/__init__.py
Toolbox/ansi_colors.py
Toolbox/pacman.py
Toolbox/tools.py
Tom_Toolbox-0.0.1.post2.dist-info/METADATA
Tom_Toolbox-0.0.1.post2.dist-info/WHEEL
Tom_Toolbox-0.0.1.post2.dist-info/top_level.txt
Tom_Toolbox-0.0.1.post2.dist-info/RECORD
